{
  "title": "Gets",
  "main_title": "Gets: Custom Fashion Platform",
  "select_style": "#Select your style",
  "recommend_style": "#Recommend style",
  "select_info": "#About",
  "gender": "GENDER",
  "age": "AGE",
  "body_type": "BODY TYPE",
  "fit": "FIT",
  "price": "PRICE",
  "woman": "woman",
  "man": "man",
  "age_10": "10s",
  "age_20": "20s",
  "age_30": "30s",
  "age_40": "40s",
  "age_50": "50s ~",
  "lower_body_fat": "chubby lower body",
  "upper_body_fat": "chubby upper body",
  "slim": "slim",
  "tall": "tall",
  "short": "short",
  "style_minimal": "Minimal",
  "style_casual": "Casual",
  "style_campus": "Campus",
  "style_office": "Office",
  "style_rock_chic": "Rock chic",
  "style_street": "Street",
  "style_amekaji": "Amekaji",
  "style_city_boy": "City boy",
  "style_feminine": "Feminine",
  "style_lovely": "Lovely",
  "style_sexy_glam": "Sexy glam",
  "fit_regular": "regular",
  "fit_over": "over",
  "fit_wide": "wide",
  "fit_semi_wide": "semi wide",
  "fit_straight": "straight",
  "fit_slim": "slim",
  "fit_tapered": "tapered",
  "fit_bootcut": "bootcut",
  "price1": "~ 100000 won",
  "price2": "~ 200000 won",
  "price3": "~ 300000 won",
  "price4": "~ 400000 won",
  "price5": "~ 500000 won",
  "price_expensive": "500000 won ~",
  "about_title": "About",
  "about_company": "About company",
  "feedback_title": "Feedback",
  "feedback_faq": "FAQ",
  "feedback_chatting": "1:1 Chatting",
  "policy_title": "Policy",
  "policy_privacy": "Privacy",
  "policy_terms": "Terms",
  "account_title": "Account",
  "account_mypage": "My page",
  "account_mystyle": "My style",
  "account_order": "Order",
  "signin": "Sign in",
  "email": "E-mail",
  "password": "Password",
  "next": "Next",
  "previous": "Previous",
  "recommend_button" : "Get Style!",
  "recommend_content" : "AI recommends a coordination set that suits your taste",
  "view_more" : "VIEW MORE",
  "recommend_content" : "AI recommends a coordination set that suits your taste",
  "not_found_title": "404. Page not found",
  "not_found_subtitle": "We can't find that page",
  "korean" : "한국어",
  "english" : "english",
  "phone_number" : "TEL : 051-510-3737, 3738, 3624",
  "address" : "2, Busandaehak-ro 63beon-gil, Geumjeong-gu, Busan, Republic of Korea PNU Science and Technology Research Center 405ho ",
  "style_guide" : "#style guide"
}